{
    "credentials": {
        "sentinel2_api": [
            {
                "user": "caesb",
                "password": "C4esb.ESEG",
                "url": "https://apihub.copernicus.eu/apihub"
            },
            {
                "user": "caesb",
                "password": "C4esb.ESEG",
                "url": "https://scihub.copernicus.eu/dhus"
            }
        ],
        "cbers_api": {
            "user": "caesb_testes@outlook.com",
            "url": "http://www2.dgi.inpe.br/stac-compose/stac/search"
        }
    }
}